[
    {
        "model": "cit.paciente",
        "pk": 1,
        "fields": {
            "nombres": "Juan Carlos",
            "apellidos": "Pérez González",
            "cedula": "1234567890",
            "fecha_nacimiento": "1990-05-15",
            "genero": "M",
            "telefono": "099-123456",
            "email": "juan.perez@email.com",
            "direccion": "Calle Principal 123, Guayaquil",
            "tipo_sangre": "O+",
            "alergias": "Ninguna",
            "observaciones_medicas": "",
            "contacto_emergencia_nombre": "María Pérez",
            "contacto_emergencia_telefono": "098-654321",
            "contacto_emergencia_relacion": "Madre",
            "clinica": 1,
            "estado": true,
            "uc": 1,
            "um": 1,
            "fc": "2025-01-10T10:00:00Z",
            "fm": "2025-01-10T10:00:00Z"
        }
    },
    {
        "model": "cit.paciente",
        "pk": 2,
        "fields": {
            "nombres": "María Fernanda",
            "apellidos": "López Vargas",
            "cedula": "0987654321",
            "fecha_nacimiento": "1985-08-20",
            "genero": "F",
            "telefono": "098-765432",
            "email": "maria.lopez@email.com",
            "direccion": "Av. Secundaria 456, Guayaquil",
            "tipo_sangre": "A+",
            "alergias": "Penicilina",
            "observaciones_medicas": "Alérgica a antibióticos betalactámicos",
            "contacto_emergencia_nombre": "Carlos López",
            "contacto_emergencia_telefono": "099-876543",
            "contacto_emergencia_relacion": "Esposo",
            "clinica": 1,
            "estado": true,
            "uc": 1,
            "um": 1,
            "fc": "2025-01-10T10:15:00Z",
            "fm": "2025-01-10T10:15:00Z"
        }
    },
    {
        "model": "cit.paciente",
        "pk": 3,
        "fields": {
            "nombres": "Pedro José",
            "apellidos": "Sánchez Morales",
            "cedula": "1111111111",
            "fecha_nacimiento": "1975-03-10",
            "genero": "M",
            "telefono": "099-111111",
            "email": "pedro.sanchez@email.com",
            "direccion": "Calle Tercera 789, Guayaquil",
            "tipo_sangre": "B+",
            "alergias": "",
            "observaciones_medicas": "Hipertensión controlada con medicación",
            "contacto_emergencia_nombre": "Ana Sánchez",
            "contacto_emergencia_telefono": "098-222222",
            "contacto_emergencia_relacion": "Esposa",
            "clinica": 1,
            "estado": true,
            "uc": 1,
            "um": 1,
            "fc": "2025-01-10T10:30:00Z",
            "fm": "2025-01-10T10:30:00Z"
        }
    },
    {
        "model": "cit.paciente",
        "pk": 4,
        "fields": {
            "nombres": "Ana María",
            "apellidos": "Rodríguez Torres",
            "cedula": "2222222222",
            "fecha_nacimiento": "1995-12-05",
            "genero": "F",
            "telefono": "098-333333",
            "email": "ana.rodriguez@email.com",
            "direccion": "Av. Cuarta 321, Guayaquil",
            "tipo_sangre": "AB+",
            "alergias": "Polen, Ácaros",
            "observaciones_medicas": "Rinitis alérgica estacional",
            "contacto_emergencia_nombre": "Luis Rodríguez",
            "contacto_emergencia_telefono": "099-444444",
            "contacto_emergencia_relacion": "Padre",
            "clinica": 1,
            "estado": true,
            "uc": 1,
            "um": 1,
            "fc": "2025-01-10T10:45:00Z",
            "fm": "2025-01-10T10:45:00Z"
        }
    },
    {
        "model": "cit.paciente",
        "pk": 5,
        "fields": {
            "nombres": "Luis Alberto",
            "apellidos": "Martínez Castro",
            "cedula": "3333333333",
            "fecha_nacimiento": "1988-06-28",
            "genero": "M",
            "telefono": "099-555555",
            "email": "luis.martinez@email.com",
            "direccion": "Calle Quinta 654, Guayaquil",
            "tipo_sangre": "O-",
            "alergias": "",
            "observaciones_medicas": "Donador universal",
            "contacto_emergencia_nombre": "Laura Castro",
            "contacto_emergencia_telefono": "098-666666",
            "contacto_emergencia_relacion": "Hermana",
            "clinica": 1,
            "estado": true,
            "uc": 1,
            "um": 1,
            "fc": "2025-01-10T11:00:00Z",
            "fm": "2025-01-10T11:00:00Z"
        }
    },
    {
        "model": "cit.paciente",
        "pk": 6,
        "fields": {
            "nombres": "Laura Patricia",
            "apellidos": "Fernández Ruiz",
            "cedula": "4444444444",
            "fecha_nacimiento": "2005-09-14",
            "genero": "F",
            "telefono": "098-777777",
            "email": "laura.fernandez@email.com",
            "direccion": "Av. Sexta 987, Guayaquil",
            "tipo_sangre": "A-",
            "alergias": "",
            "observaciones_medicas": "Paciente menor de edad",
            "contacto_emergencia_nombre": "Patricia Ruiz",
            "contacto_emergencia_telefono": "099-888888",
            "contacto_emergencia_relacion": "Madre",
            "clinica": 1,
            "estado": true,
            "uc": 1,
            "um": 1,
            "fc": "2025-01-10T11:15:00Z",
            "fm": "2025-01-10T11:15:00Z"
        }
    },
    {
        "model": "cit.paciente",
        "pk": 7,
        "fields": {
            "nombres": "Roberto Carlos",
            "apellidos": "Gómez Silva",
            "cedula": "5555555555",
            "fecha_nacimiento": "1965-11-22",
            "genero": "M",
            "telefono": "099-999999",
            "email": "roberto.gomez@email.com",
            "direccion": "Calle Séptima 159, Guayaquil",
            "tipo_sangre": "B-",
            "alergias": "Yodo",
            "observaciones_medicas": "Alergia a contrastes yodados. Diabetes tipo 2 controlada.",
            "contacto_emergencia_nombre": "Carmen Silva",
            "contacto_emergencia_telefono": "098-101010",
            "contacto_emergencia_relacion": "Esposa",
            "clinica": 1,
            "estado": true,
            "uc": 1,
            "um": 1,
            "fc": "2025-01-10T11:30:00Z",
            "fm": "2025-01-10T11:30:00Z"
        }
    },
    {
        "model": "cit.paciente",
        "pk": 8,
        "fields": {
            "nombres": "Carmen Lucía",
            "apellidos": "Herrera Ortiz",
            "cedula": "6666666666",
            "fecha_nacimiento": "1992-04-18",
            "genero": "F",
            "telefono": "098-121212",
            "email": "carmen.herrera@email.com",
            "direccion": "Av. Octava 753, Guayaquil",
            "tipo_sangre": "AB-",
            "alergias": "Látex",
            "observaciones_medicas": "Alergia al látex - usar guantes de nitrilo",
            "contacto_emergencia_nombre": "Jorge Herrera",
            "contacto_emergencia_telefono": "099-131313",
            "contacto_emergencia_relacion": "Hermano",
            "clinica": 1,
            "estado": true,
            "uc": 1,
            "um": 1,
            "fc": "2025-01-10T11:45:00Z",
            "fm": "2025-01-10T11:45:00Z"
        }
    },
    {
        "model": "cit.paciente",
        "pk": 9,
        "fields": {
            "nombres": "Diego Andrés",
            "apellidos": "Ramírez Vega",
            "cedula": "7777777777",
            "fecha_nacimiento": "2010-07-05",
            "genero": "M",
            "telefono": "099-141414",
            "email": "",
            "direccion": "Calle Novena 951, Guayaquil",
            "tipo_sangre": "O+",
            "alergias": "",
            "observaciones_medicas": "Paciente pediátrico",
            "contacto_emergencia_nombre": "Mónica Vega",
            "contacto_emergencia_telefono": "098-151515",
            "contacto_emergencia_relacion": "Madre",
            "clinica": 1,
            "estado": true,
            "uc": 1,
            "um": 1,
            "fc": "2025-01-10T12:00:00Z",
            "fm": "2025-01-10T12:00:00Z"
        }
    },
    {
        "model": "cit.paciente",
        "pk": 10,
        "fields": {
            "nombres": "Sofía Elena",
            "apellidos": "Castro Méndez",
            "cedula": "8888888888",
            "fecha_nacimiento": "1958-02-28",
            "genero": "F",
            "telefono": "098-161616",
            "email": "sofia.castro@email.com",
            "direccion": "Av. Décima 357, Guayaquil",
            "tipo_sangre": "A+",
            "alergias": "Sulfamidas",
            "observaciones_medicas": "Paciente adulta mayor. Prótesis dental completa superior.",
            "contacto_emergencia_nombre": "Raúl Castro",
            "contacto_emergencia_telefono": "099-171717",
            "contacto_emergencia_relacion": "Hijo",
            "clinica": 1,
            "estado": true,
            "uc": 1,
            "um": 1,
            "fc": "2025-01-10T12:15:00Z",
            "fm": "2025-01-10T12:15:00Z"
        }
    }
]
